numerapi/__init__.py
numerapi/base_api.py
numerapi/cli.py
numerapi/cryptoapi.py
numerapi/numerapi.py
numerapi/py.typed
numerapi/signalsapi.py
numerapi/utils.py
numerapi-2.22.0.dist-info/licenses/LICENSE
numerapi-2.22.0.dist-info/METADATA
numerapi-2.22.0.dist-info/WHEEL
numerapi-2.22.0.dist-info/entry_points.txt
numerapi-2.22.0.dist-info/top_level.txt
numerapi-2.22.0.dist-info/RECORD
