Metadata-Version: 2.4
Name: numerapi
Version: 2.22.0
Summary: Automatically download and upload data for the Numerai machine learning competition
Home-page: https://github.com/uuazed/numerapi
Maintainer: uuazed
Maintainer-email: uuazed@gmail.com
License: MIT License
Platform: OS Independent
Classifier: Development Status :: 5 - Production/Stable
Classifier: Environment :: Console
Classifier: Intended Audience :: Science/Research
Classifier: License :: OSI Approved :: MIT License
Classifier: Operating System :: OS Independent
Classifier: Programming Language :: Python
Classifier: Programming Language :: Python :: 3
Classifier: Topic :: Scientific/Engineering
License-File: LICENSE
Requires-Dist: requests
Requires-Dist: pytz
Requires-Dist: python-dateutil
Requires-Dist: tqdm>=4.29.1
Requires-Dist: click>=7.0
Requires-Dist: pandas>=1.1.0
Dynamic: classifier
Dynamic: description
Dynamic: description-content-type
Dynamic: home-page
Dynamic: license
Dynamic: license-file
Dynamic: maintainer
Dynamic: maintainer-email
Dynamic: platform
Dynamic: requires-dist
Dynamic: summary
